imgz_cli/__init__.py
imgz_cli/cli.py
imgz_cli/version.py
imgz_cli-0.1.1.dist-info/entry_points.txt
imgz_cli-0.1.1.dist-info/LICENSE
imgz_cli-0.1.1.dist-info/WHEEL
imgz_cli-0.1.1.dist-info/METADATA
imgz_cli-0.1.1.dist-info/RECORD
