Metadata-Version: 2.1
Name: imgz_cli
Version: 0.1.1
Summary: imgz-cli uploads images.
Home-page: https://gitlab.com/stavros/imgz-cli
License: UNKNOWN
Keywords: imgz, image, imgur
Author: Stavros Korokithakis
Author-email: hi@stavros.io
Requires-Python: >=3.5
Classifier: License :: OSI Approved :: MIT License
Classifier: Programming Language :: Python :: 3
Requires-Dist: requests
Requires-Dist: pyperclip
